fat_ffipd/Config.py
fat_ffipd/__init__.py
fat_ffipd/main.py
fat_ffipd/background/__init__.py
fat_ffipd/db/__init__.py
fat_ffipd/routes/__init__.py
fat_ffipd/test/TestFramework.py
fat_ffipd/test/__init__.py
fat_ffipd/test/db/TestApiKey.py
fat_ffipd/test/db/TestUser.py
fat_ffipd/test/db/__init__.py
fat_ffipd/test/misc/TestApiCalls.py
fat_ffipd/test/misc/TestBackgroundTasks.py
fat_ffipd/test/misc/TestConfig.py
fat_ffipd/test/misc/TestErrorHandling.py
fat_ffipd/test/misc/TestServer.py
fat_ffipd/test/misc/__init__.py
fat_ffipd/test/routes/TestForgotRoute.py
fat_ffipd/test/routes/TestLoginRoute.py
fat_ffipd/test/routes/TestProfileRoute.py
fat_ffipd/test/routes/TestRegisterRoute.py
fat_ffipd/test/routes/TestStaticRoutes.py
fat_ffipd/test/routes/__init__.py
fat_ffipd/test/routes/api/TestApiKeyRoute.py
fat_ffipd/test/routes/api/__init__.py
fat_ffipd-0.4.2.data/scripts/backup.sh
fat_ffipd-0.4.2.data/scripts/printenv
fat_ffipd-0.4.2.data/scripts/restore.sh
fat_ffipd-0.4.2.dist-info/LICENSE
fat_ffipd-0.4.2.dist-info/METADATA
fat_ffipd-0.4.2.dist-info/WHEEL
fat_ffipd-0.4.2.dist-info/top_level.txt
fat_ffipd-0.4.2.dist-info/RECORD
