Metadata-Version: 2.1
Name: fat-ffipd
Version: 0.4.2
Summary: Flask Application Template - For Fast Initial Project Develoment
Home-page: https://gitlab.namibsun.net/namibsun/python/fat-ffipd
Author: Hermann Krumrey
Author-email: hermann@krumreyh.com
License: GNU GPL3
Platform: UNKNOWN
Classifier: License :: OSI Approved :: GNU General Public License v3 (GPLv3)
Requires-Dist: cherrypy
Requires-Dist: Flask
Requires-Dist: werkzeug
Requires-Dist: flask-sqlalchemy
Requires-Dist: flask-login
Requires-Dist: puffotter[crypto,flask]
